.travis.yml
CHANGES.rst
MANIFEST.in
README.rst
setup.py
tox.ini
/home/blackwithwhite/Work/ged-soa/stats/src/pyhll/src/hll.c
/home/blackwithwhite/Work/ged-soa/stats/src/pyhll/src/hll_constants.c
deps/murmurhash3/MurmurHash3.cpp
deps/murmurhash3/MurmurHash3.h
deps/murmurhash3/waf
deps/murmurhash3/wscript
pyhll/__init__.py
pyhll/hll.c
pyhll/hll.pyx
pyhll.egg-info/PKG-INFO
pyhll.egg-info/SOURCES.txt
pyhll.egg-info/dependency_links.txt
pyhll.egg-info/not-zip-safe
pyhll.egg-info/top_level.txt
pyhll/tests/__init__.py
pyhll/tests/base.py
pyhll/tests/test_cardinality.py
pyhll/tests/test_utils.py
src/hll.c
src/hll.h
src/hll_constants.c
src/hll_constants.h